sym/shared/cli/__init__.py
sym/shared/cli/data/__init__.py
sym/shared/cli/data/global_options_base.py
sym/shared/cli/decorators.py
sym/shared/cli/errors.py
sym/shared/cli/helpers/__init__.py
sym/shared/cli/helpers/boto.py
sym/shared/cli/helpers/config/__init__.py
sym/shared/cli/helpers/config/base.py
sym/shared/cli/helpers/config/sym_config_file.py
sym/shared/cli/helpers/contexts.py
sym/shared/cli/helpers/envvar_option.py
sym/shared/cli/helpers/init.py
sym/shared/cli/helpers/io.py
sym/shared/cli/helpers/keywords_to_options.py
sym/shared/cli/helpers/os.py
sym/shared/cli/helpers/segment.py
sym/shared/cli/helpers/sentry.py
sym/shared/cli/helpers/sym_group.py
sym/shared/cli/helpers/tee.py
sym/shared/cli/helpers/updater.py
sym/shared/cli/helpers/util.py
sym/shared/cli/tests/__init__.py
sym/shared/cli/tests/conftest.py
sym/shared/cli/tests/helpers/__init__.py
sym/shared/cli/tests/helpers/capture.py
sym/shared/cli/tests/helpers/sandbox.py
sym/shared/cli/tests/helpers/test_keywords_to_options.py
sym/shared/cli/tests/helpers/test_push_env.py
sym/shared/cli/tests/helpers/test_safe_create.py
sym/shared/cli/version.py
sym_shared_cli-0.2.5.dist-info/WHEEL
sym_shared_cli-0.2.5.dist-info/METADATA
sym_shared_cli-0.2.5.dist-info/RECORD
