Metadata-Version: 2.1
Name: sym-shared-cli
Version: 0.2.5
Summary: Sym's CLI shared library
Home-page: https://symops.com/
Author: SymOps, Inc.
Author-email: pypi@symops.io
Requires-Python: >=3.8,<4.0
Classifier: Operating System :: OS Independent
Classifier: Programming Language :: Python :: 3
Classifier: Programming Language :: Python :: 3.8
Classifier: Programming Language :: Python :: 3.9
Classifier: Programming Language :: Python :: 3.10
Classifier: Programming Language :: Python :: 3.11
Classifier: Programming Language :: Python :: 3
Requires-Dist: analytics-python (>=1.3.1,<2.0.0)
Requires-Dist: click (>=8.0.4,<9.0.0)
Requires-Dist: click-option-group (>=0.5.1,<0.6.0)
Requires-Dist: immutables (>=0.19,<0.20)
Requires-Dist: portalocker (>=2.0.0,<3.0.0)
Requires-Dist: requests (>=2.25,<3.0)
Requires-Dist: semver (>=2.13.0,<3.0.0)
Requires-Dist: sentry-sdk (>=1.0.0,<2.0.0)
Project-URL: Documentation, https://docs.symops.com/
